ipyanchorviz/__init__.py
ipyanchorviz/_version.py
ipyanchorviz/anchorviz.py
ipyanchorviz/labextension/package.json
ipyanchorviz/labextension/static/145.364cb8f857fbf54e3b38.js
ipyanchorviz/labextension/static/202.971d9bc912a7d0fb50d1.js
ipyanchorviz/labextension/static/221.ba0490537a656b0ebb99.js
ipyanchorviz/labextension/static/493.6ed9e69a1dd71ec1bcab.js
ipyanchorviz/labextension/static/543.25cf7106ec0f141ee09a.js
ipyanchorviz/labextension/static/543.25cf7106ec0f141ee09a.js.LICENSE.txt
ipyanchorviz/labextension/static/884.1a0d1531c67c8a4cc9fc.js
ipyanchorviz/labextension/static/remoteEntry.aefb2f9eab634f8797c0.js
ipyanchorviz/labextension/static/style.js
ipyanchorviz/labextension/static/third-party-licenses.json
ipyanchorviz/nbextension/extension.js
ipyanchorviz/nbextension/index.js
ipyanchorviz/nbextension/index.js.LICENSE.txt
ipyanchorviz-0.3.0.data/data/etc/jupyter/nbconfig/notebook.d/ipyanchorviz.json
ipyanchorviz-0.3.0.data/data/share/jupyter/labextensions/ipyanchorviz/install.json
ipyanchorviz-0.3.0.data/data/share/jupyter/labextensions/ipyanchorviz/package.json
ipyanchorviz-0.3.0.data/data/share/jupyter/labextensions/ipyanchorviz/static/145.364cb8f857fbf54e3b38.js
ipyanchorviz-0.3.0.data/data/share/jupyter/labextensions/ipyanchorviz/static/202.971d9bc912a7d0fb50d1.js
ipyanchorviz-0.3.0.data/data/share/jupyter/labextensions/ipyanchorviz/static/221.ba0490537a656b0ebb99.js
ipyanchorviz-0.3.0.data/data/share/jupyter/labextensions/ipyanchorviz/static/493.6ed9e69a1dd71ec1bcab.js
ipyanchorviz-0.3.0.data/data/share/jupyter/labextensions/ipyanchorviz/static/543.25cf7106ec0f141ee09a.js
ipyanchorviz-0.3.0.data/data/share/jupyter/labextensions/ipyanchorviz/static/543.25cf7106ec0f141ee09a.js.LICENSE.txt
ipyanchorviz-0.3.0.data/data/share/jupyter/labextensions/ipyanchorviz/static/884.1a0d1531c67c8a4cc9fc.js
ipyanchorviz-0.3.0.data/data/share/jupyter/labextensions/ipyanchorviz/static/remoteEntry.aefb2f9eab634f8797c0.js
ipyanchorviz-0.3.0.dist-info/LICENSE
ipyanchorviz-0.3.0.dist-info/METADATA
ipyanchorviz-0.3.0.dist-info/WHEEL
ipyanchorviz-0.3.0.dist-info/top_level.txt
ipyanchorviz-0.3.0.dist-info/RECORD
