Metadata-Version: 2.1
Name: ipyanchorviz
Version: 0.3.0
Summary: A Custom Jupyter Widget Library
Home-page: https://github.com/ORNL/ipyanchorviz
Author: Nathan Martindale
Author-email: martindalena@ornl.gov
License: BSD 3-Clause License
Keywords: ipython,widgets,Jupyter,JupyterLab,JupyterLab3
Classifier: License :: OSI Approved :: BSD License
Classifier: Development Status :: 4 - Beta
Classifier: Framework :: IPython
Classifier: Intended Audience :: Developers
Classifier: Intended Audience :: Science/Research
Classifier: Programming Language :: Python
Classifier: Programming Language :: Python :: 3.7
Classifier: Programming Language :: Python :: 3.8
Classifier: Programming Language :: Python :: 3.9
Classifier: Programming Language :: Python :: 3.10
Classifier: Framework :: Jupyter
Classifier: Framework :: Jupyter :: JupyterLab
Classifier: Framework :: Jupyter :: JupyterLab :: 3
Classifier: Framework :: Jupyter :: JupyterLab :: Extensions
Classifier: Framework :: Jupyter :: JupyterLab :: Extensions :: Prebuilt
Requires-Python: >=3.7
License-File: LICENSE
Requires-Dist: ipywidgets<9,>=7.6.0
Requires-Dist: pandas
